{
    "wallpapers": [
                    {
                        "author": "Travis Hall",
                        "url": "https://raw.githubusercontent.com/RippedThemer/Glare-Void/master/Wallpapers/flowers.png",
                        "name": "Flowers"
                    },
                    {
                        "author": "Travis Hall",
                        "url": "https://raw.githubusercontent.com/RippedThemer/Glare-Void/master/Wallpapers/flowers2.png",
                        "name": "Flowers2"
                    },
                    {
                        "author": "Travis Hall",
                        "url": "https://raw.githubusercontent.com/RippedThemer/Glare-Void/master/Wallpapers/flowers3.png",
                        "name": "Flowers3"
                    },
                    {
                        "author": "Travis Hall",
                        "url": "https://raw.githubusercontent.com/RippedThemer/Glare-Void/master/Wallpapers/flowers4.png",
                        "name": "Flowers4"
                    },
                    {
                        "author": "Travis Hall",
                        "url": "https://raw.githubusercontent.com/RippedThemer/Glare-Void/master/Wallpapers/flowers5.png",
                        "name": "Flowers5"
                    },
                    {
                        "author": "Travis Hall",
                        "url": "https://raw.githubusercontent.com/RippedThemer/Glare-Void/master/Wallpapers/moments.png",
                        "name": "Moments"
                     },
                     {
                        "author": "Travis Hall",
                        "url": "https://raw.githubusercontent.com/RippedThemer/Glare-Void/master/Wallpapers/moments2.png",
                        "name": "Moments2"
                    },
                    {
                        "author": "Travis Hall",
                        "url": "https://raw.githubusercontent.com/RippedThemer/Glare-Void/master/Wallpapers/moments3.png",
                        "name": "Moments3"
                    },
                    {
                        "author": "Travis Hall",
                        "url": "https://raw.githubusercontent.com/RippedThemer/Glare-Void/master/Wallpapers/moments4.png",
                        "name": "Moments4"
                    },
                    {
                        "author": "Travis Hall",
                        "url": "https://raw.githubusercontent.com/RippedThemer/Glare-Void/master/Wallpapers/moments5.png",
                        "name": "Moments5"
                    },
                    {
                        "author": "Travis Hall",
                        "url": "https://raw.githubusercontent.com/RippedThemer/Glare-Void/master/Wallpapers/paper.png",
                        "name": "Paper"
                    },
                    {
                        "author": "Travis Hall",
                        "url": "https://raw.githubusercontent.com/RippedThemer/Glare-Void/master/Wallpapers/paper2.png",
                        "name": "Paper2"
                   },
                   {            
                       "author": "Travis Hall",
                        "url": "https://raw.githubusercontent.com/RippedThemer/Glare-Void/master/Wallpapers/paper3.png",
                        "name": "Paper3"
                    },
                    {
                        "author": "Travis Hall",
                        "url": "https://raw.githubusercontent.com/RippedThemer/Glare-Void/master/Wallpapers/paper4.png",
                        "name": "Paper4"
                    },
                    {
			            "author": "Travis Hall",
			            "url": "https://raw.githubusercontent.com/RippedThemer/Glare-Void/master/Wallpapers/paper5.png",
			            "name": "Paper5"
		            },
                    {
                        "author": "Travis Hall",
                        "url": "https://raw.githubusercontent.com/RippedThemer/Glare-Void/master/Wallpapers/paper6.png",
                        "name": "Paper6"
                    }
          ]
}